[
    {
        "name": "Lọc nhớt động cơ Bosch",
        "unit_price": 185000.0,
        "unit": "Cái",
        "supplier": "Công ty TNHH Phụ tùng Bình Minh",
        "inventory": 5,
        "image_url": "https://res.cloudinary.com/dbxtbus46/image/upload/v1765352904/360_F_641732036_if4Eq4gHSoPiDmmxIcim0FDPkjWGYlOq_htvlsc.jpg"
    },
    {
        "name": "Dầu động cơ Castrol EDGE 5W-40",
        "unit_price": 1150000.0,
        "unit": "Can 4 Lít",
        "supplier": "Đại lý dầu nhớt Á Châu",
        "inventory": 5,
        "image_url": "https://res.cloudinary.com/dbxtbus46/image/upload/v1765352904/360_F_641732036_if4Eq4gHSoPiDmmxIcim0FDPkjWGYlOq_htvlsc.jpg"
    },
    {
        "name": "Má phanh Ceramic trước",
        "unit_price": 950000.0,
        "unit": "Bộ",
        "supplier": "Nhà cung cấp Phanh Việt",
        "inventory": 11,
        "image_url": "https://res.cloudinary.com/dbxtbus46/image/upload/v1765352904/360_F_641732036_if4Eq4gHSoPiDmmxIcim0FDPkjWGYlOq_htvlsc.jpg"
    },
    {
        "name": "Bugi bạch kim Denso",
        "unit_price": 150000.0,
        "unit": "Cái",
        "supplier": "N/A",
        "inventory": 56,
        "image_url": "https://res.cloudinary.com/dbxtbus46/image/upload/v1765352904/360_F_641732036_if4Eq4gHSoPiDmmxIcim0FDPkjWGYlOq_htvlsc.jpg"
    },
    {
        "name": "Ắc quy GS 12V-60AH",
        "unit_price": 1900000.0,
        "unit": "Bình",
        "supplier": "Ắc quy chính hãng Miền Nam",
        "inventory": 16,
        "image_url": "https://res.cloudinary.com/dbxtbus46/image/upload/v1765352904/360_F_641732036_if4Eq4gHSoPiDmmxIcim0FDPkjWGYlOq_htvlsc.jpg"
    },
    {
        "name": "Cần gạt nước Silicone (2 chiếc)",
        "unit_price": 380000.0,
        "unit": "Bộ",
        "supplier": "Công ty Phụ kiện xe hơi 3A",
        "inventory": 56,
        "image_url": "https://res.cloudinary.com/dbxtbus46/image/upload/v1765352904/360_F_641732036_if4Eq4gHSoPiDmmxIcim0FDPkjWGYlOq_htvlsc.jpg"
    },
    {
        "name": "Nước làm mát Blue (2L)",
        "unit_price": 250000.0,
        "unit": "Chai",
        "supplier": "N/A",
        "inventory": 56,
        "image_url": "https://res.cloudinary.com/dbxtbus46/image/upload/v1765352904/360_F_641732036_if4Eq4gHSoPiDmmxIcim0FDPkjWGYlOq_htvlsc.jpg"
    },
    {
        "name": "Đèn pha Halogen H4 Philips",
        "unit_price": 550000.0,
        "unit": "Cái",
        "supplier": "Nhà phân phối đèn xe Quang Phát",
        "inventory": 526,
        "image_url": "https://res.cloudinary.com/dbxtbus46/image/upload/v1765352904/360_F_641732036_if4Eq4gHSoPiDmmxIcim0FDPkjWGYlOq_htvlsc.jpg"
    },
    {
        "name": "Cao su chân máy",
        "unit_price": 1250000.0,
        "unit": "Cái",
        "supplier": "Phụ tùng máy Vĩnh Phát",
        "inventory": 5116,
        "image_url": "https://res.cloudinary.com/dbxtbus46/image/upload/v1765352904/360_F_641732036_if4Eq4gHSoPiDmmxIcim0FDPkjWGYlOq_htvlsc.jpg"
    }
]